{"sections":{"main":{"type":"main-collection","blocks":{"5ccbfd38-1396-4046-8cb0-eb607fc18fde":{"type":"collection","settings":{"collection":"twilight-buddies","product":"","collection_text_color":"#005178","collection_bg_color":"#f4f1eb","collection_bg_gradient":"","color_overlay_bg":"#ffffff","overlay_opacity":10,"color_overlay_text":"#333333"}}},"block_order":["5ccbfd38-1396-4046-8cb0-eb607fc18fde"],"settings":{"enable_feature_header":true,"grid":4,"grid_mobile":"2","pagination_limit":34,"show_total":true,"show_vendor":false,"show_filters":true,"show_filter_prod_counts":true,"show_sort_by":true,"show_featured":true}},"799f9e1b-42a7-4d10-ba85-7eb21b2f6a64":{"type":"custom-liquid","settings":{"custom_liquid":"<div style=\"padding:56.25% 0 0 0;position:relative;\"><iframe src=\"https:\/\/player.vimeo.com\/video\/790761359?h=4506bba6aa&amp;badge=0&amp;autopause=0&amp;player_id=0&amp;app_id=58479\" frameborder=\"0\" allow=\"autoplay; fullscreen; picture-in-picture\" allowfullscreen style=\"position:absolute;top:0;left:0;width:100%;height:100%;border-radius:35px\" title=\"Dream Buddies\"><\/iframe><\/div><script src=\"https:\/\/player.vimeo.com\/api\/player.js\"><\/script>"}}},"order":["main","799f9e1b-42a7-4d10-ba85-7eb21b2f6a64"]}